{
  "is_binned": true, 
  "data": [
    1164.0, 
    1523.0, 
    883.0, 
    750.0, 
    840.0, 
    1083.0, 
    548.0, 
    521.0
  ], 
  "signal": {
    "HNL-mu-m70-Vsq5.0em05-prompt": {
      "down": [
        0.0009393556927184536, 
        0.0023472298166043845, 
        0.0024201848954320303, 
        0.0016440182769280796, 
        0.00029070008895359933, 
        0.001139493798106116, 
        0.0010919506470424352, 
        0.00205818609653114
      ], 
      "nominal": [
        0.0012556555739138275, 
        0.004887164541287348, 
        0.005504961307451595, 
        0.0027745396364480257, 
        0.00029070008895359933, 
        0.0024032851215451956, 
        0.0016924981900956482, 
        0.00436085945693776
      ], 
      "up": [
        0.0009393556927184536, 
        0.0023472298166043845, 
        0.0024201848954320303, 
        0.0016440182769280796, 
        0.00029070008895359933, 
        0.001139493798106116, 
        0.0010919506470424352, 
        0.00205818609653114
      ], 
      "bins": [
        [
          8.5, 
          9.5
        ], 
        [
          9.5, 
          10.5
        ], 
        [
          10.5, 
          11.5
        ], 
        [
          11.5, 
          12.5
        ], 
        [
          12.5, 
          13.5
        ], 
        [
          13.5, 
          14.5
        ], 
        [
          14.5, 
          15.5
        ], 
        [
          15.5, 
          16.5
        ]
      ]
    }, 
    "HNL-tau-m25-Vsq5.0em04-displaced": {
      "down": [
        0.25832294872552886, 
        0.4670967134306364, 
        0.22361392265112623, 
        0.0, 
        0.1371817132586711, 
        0.349328235372842, 
        0.2297524123908252, 
        0.0
      ], 
      "nominal": [
        2.166332289400118, 
        7.731846725983429, 
        1.9164565080447802, 
        0.0, 
        0.9902974334395931, 
        4.274780034871374, 
        1.212446782755498, 
        0.0
      ], 
      "up": [
        0.25832294872552886, 
        0.4670967134306364, 
        0.22361392265112623, 
        0.0, 
        0.1371817132586711, 
        0.349328235372842, 
        0.2297524123908252, 
        0.0
      ], 
      "bins": [
        [
          8.5, 
          9.5
        ], 
        [
          9.5, 
          10.5
        ], 
        [
          10.5, 
          11.5
        ], 
        [
          11.5, 
          12.5
        ], 
        [
          12.5, 
          13.5
        ], 
        [
          13.5, 
          14.5
        ], 
        [
          14.5, 
          15.5
        ], 
        [
          15.5, 
          16.5
        ]
      ]
    }, 
    "HNL-e-m12.5-Vsq2.5em05-displaced": {
      "down": [
        0.0, 
        0.0, 
        0.0, 
        0.0, 
        0.0029537348487548294, 
        0.0, 
        0.0, 
        0.0
      ], 
      "nominal": [
        0.0, 
        0.0, 
        0.0, 
        0.0, 
        0.0029537348487548294, 
        0.0, 
        0.0, 
        0.0
      ], 
      "up": [
        0.0, 
        0.0, 
        0.0, 
        0.0, 
        0.0029537348487548294, 
        0.0, 
        0.0, 
        0.0
      ], 
      "bins": [
        [
          8.5, 
          9.5
        ], 
        [
          9.5, 
          10.5
        ], 
        [
          10.5, 
          11.5
        ], 
        [
          11.5, 
          12.5
        ], 
        [
          12.5, 
          13.5
        ], 
        [
          13.5, 
          14.5
        ], 
        [
          14.5, 
          15.5
        ], 
        [
          15.5, 
          16.5
        ]
      ]
    }, 
    "HNL-e-m40-Vsq6.0em06-prompt": {
      "down": [
        0.0, 
        0.0, 
        0.0005397475697100162, 
        0.0, 
        0.0, 
        0.0, 
        0.0, 
        0.0
      ], 
      "nominal": [
        0.0, 
        0.0, 
        0.0005397475697100162, 
        0.0, 
        0.0, 
        0.0, 
        0.0, 
        0.0
      ], 
      "up": [
        0.0, 
        0.0, 
        0.0005397475697100162, 
        0.0, 
        0.0, 
        0.0, 
        0.0, 
        0.0
      ], 
      "bins": [
        [
          8.5, 
          9.5
        ], 
        [
          9.5, 
          10.5
        ], 
        [
          10.5, 
          11.5
        ], 
        [
          11.5, 
          12.5
        ], 
        [
          12.5, 
          13.5
        ], 
        [
          13.5, 
          14.5
        ], 
        [
          14.5, 
          15.5
        ], 
        [
          15.5, 
          16.5
        ]
      ]
    }, 
    "HNL-tau-m10-Vsq5.0em04-displaced": {
      "down": [
        0.45174702516384446, 
        0.0, 
        0.0, 
        0.0, 
        0.524806835258396, 
        0.0, 
        0.0, 
        0.0
      ], 
      "nominal": [
        7.711103754426082, 
        0.0, 
        0.0, 
        0.0, 
        5.455968954435342, 
        0.0, 
        0.0, 
        0.0
      ], 
      "up": [
        0.45174702516384446, 
        0.0, 
        0.0, 
        0.0, 
        0.524806835258396, 
        0.0, 
        0.0, 
        0.0
      ], 
      "bins": [
        [
          8.5, 
          9.5
        ], 
        [
          9.5, 
          10.5
        ], 
        [
          10.5, 
          11.5
        ], 
        [
          11.5, 
          12.5
        ], 
        [
          12.5, 
          13.5
        ], 
        [
          13.5, 
          14.5
        ], 
        [
          14.5, 
          15.5
        ], 
        [
          15.5, 
          16.5
        ]
      ]
    }, 
    "HNL-e-m70-Vsq6.0em05-prompt": {
      "down": [
        0.0, 
        0.0012434557545930147, 
        0.0, 
        0.0, 
        0.0, 
        0.0, 
        0.0, 
        0.0
      ], 
      "nominal": [
        0.0, 
        0.0012434557545930147, 
        0.0, 
        0.0, 
        0.0, 
        0.0, 
        0.0, 
        0.0
      ], 
      "up": [
        0.0, 
        0.0012434557545930147, 
        0.0, 
        0.0, 
        0.0, 
        0.0, 
        0.0, 
        0.0
      ], 
      "bins": [
        [
          8.5, 
          9.5
        ], 
        [
          9.5, 
          10.5
        ], 
        [
          10.5, 
          11.5
        ], 
        [
          11.5, 
          12.5
        ], 
        [
          12.5, 
          13.5
        ], 
        [
          13.5, 
          14.5
        ], 
        [
          14.5, 
          15.5
        ], 
        [
          15.5, 
          16.5
        ]
      ]
    }, 
    "HNL-tau-m12.5-Vsq5.0em04-displaced": {
      "down": [
        0.5991701321797124, 
        0.2654061469316074, 
        0.0, 
        0.0, 
        0.39514744980247063, 
        0.5771219406015659, 
        0.0, 
        0.0
      ], 
      "nominal": [
        8.794256408933178, 
        1.971414833007826, 
        0.0, 
        0.0, 
        4.890649758231667, 
        2.644101866771215, 
        0.0, 
        0.0
      ], 
      "up": [
        0.5991701321797124, 
        0.2654061469316074, 
        0.0, 
        0.0, 
        0.39514744980247063, 
        0.5771219406015659, 
        0.0, 
        0.0
      ], 
      "bins": [
        [
          8.5, 
          9.5
        ], 
        [
          9.5, 
          10.5
        ], 
        [
          10.5, 
          11.5
        ], 
        [
          11.5, 
          12.5
        ], 
        [
          12.5, 
          13.5
        ], 
        [
          13.5, 
          14.5
        ], 
        [
          14.5, 
          15.5
        ], 
        [
          15.5, 
          16.5
        ]
      ]
    }, 
    "HNL-mu-m10-Vsq2.5em05-displaced": {
      "down": [
        0.0, 
        0.0, 
        0.0, 
        0.002930779661102751, 
        0.0, 
        0.0, 
        0.0, 
        0.008609302934365006
      ], 
      "nominal": [
        0.0, 
        0.0, 
        0.0, 
        0.002930779661102751, 
        0.0, 
        0.0, 
        0.0, 
        0.008609302934365006
      ], 
      "up": [
        0.0, 
        0.0, 
        0.0, 
        0.002930779661102751, 
        0.0, 
        0.0, 
        0.0, 
        0.008609302934365006
      ], 
      "bins": [
        [
          8.5, 
          9.5
        ], 
        [
          9.5, 
          10.5
        ], 
        [
          10.5, 
          11.5
        ], 
        [
          11.5, 
          12.5
        ], 
        [
          12.5, 
          13.5
        ], 
        [
          13.5, 
          14.5
        ], 
        [
          14.5, 
          15.5
        ], 
        [
          15.5, 
          16.5
        ]
      ]
    }, 
    "HNL-mu-m60-Vsq6.0em06-prompt": {
      "down": [
        0.00037733438358967186, 
        0.000534035178252899, 
        0.000596852707678312, 
        0.0007783279750294931, 
        0.00023753872141242025, 
        0.0007950731560183842, 
        0.0008479088025420415, 
        0.0008931849747025929
      ], 
      "nominal": [
        0.0005318318400532007, 
        0.0008090364024974405, 
        0.0015122216194868086, 
        0.0016360125713981689, 
        0.00023753872141242025, 
        0.0018605843558907507, 
        0.0015096237743273378, 
        0.0020321002160198984
      ], 
      "up": [
        0.00037733438358967186, 
        0.000534035178252899, 
        0.000596852707678312, 
        0.0007783279750294931, 
        0.00023753872141242025, 
        0.0007950731560183842, 
        0.0008479088025420415, 
        0.0008931849747025929
      ], 
      "bins": [
        [
          8.5, 
          9.5
        ], 
        [
          9.5, 
          10.5
        ], 
        [
          10.5, 
          11.5
        ], 
        [
          11.5, 
          12.5
        ], 
        [
          12.5, 
          13.5
        ], 
        [
          13.5, 
          14.5
        ], 
        [
          14.5, 
          15.5
        ], 
        [
          15.5, 
          16.5
        ]
      ]
    }, 
    "HNL-tau-m20-Vsq5.0em04-displaced": {
      "down": [
        0.4382755680550347, 
        0.6849971454675767, 
        0.0, 
        0.0, 
        0.5539177932291295, 
        0.5225758770716432, 
        0.0, 
        0.0
      ], 
      "nominal": [
        3.37544333871451, 
        9.130823577343882, 
        0.0, 
        0.0, 
        2.8008757087000378, 
        5.725663954856006, 
        0.0, 
        0.0
      ], 
      "up": [
        0.4382755680550347, 
        0.6849971454675767, 
        0.0, 
        0.0, 
        0.5539177932291295, 
        0.5225758770716432, 
        0.0, 
        0.0
      ], 
      "bins": [
        [
          8.5, 
          9.5
        ], 
        [
          9.5, 
          10.5
        ], 
        [
          10.5, 
          11.5
        ], 
        [
          11.5, 
          12.5
        ], 
        [
          12.5, 
          13.5
        ], 
        [
          13.5, 
          14.5
        ], 
        [
          14.5, 
          15.5
        ], 
        [
          15.5, 
          16.5
        ]
      ]
    }, 
    "HNL-mu-m20-Vsq2.5em05-displaced": {
      "down": [
        0.0, 
        0.0, 
        2.384608722150603e-05, 
        1.552718869209882e-05, 
        0.0003356789747933923, 
        0.0, 
        0.0, 
        0.04343200006409715
      ], 
      "nominal": [
        0.0, 
        0.0, 
        2.384608722150603e-05, 
        1.552718869209882e-05, 
        0.0003356789747933923, 
        0.0, 
        0.0, 
        0.04355122861162492
      ], 
      "up": [
        0.0, 
        0.0, 
        2.384608722150603e-05, 
        1.552718869209882e-05, 
        0.0003356789747933923, 
        0.0, 
        0.0, 
        0.04343200006409715
      ], 
      "bins": [
        [
          8.5, 
          9.5
        ], 
        [
          9.5, 
          10.5
        ], 
        [
          10.5, 
          11.5
        ], 
        [
          11.5, 
          12.5
        ], 
        [
          12.5, 
          13.5
        ], 
        [
          13.5, 
          14.5
        ], 
        [
          14.5, 
          15.5
        ], 
        [
          15.5, 
          16.5
        ]
      ]
    }, 
    "HNL-tau-m60-Vsq2.0em03-prompt": {
      "down": [
        0.024500922072510388, 
        0.07723341977373575, 
        0.09406905627862173, 
        0.11239901320032171, 
        0.02477813238324357, 
        0.06961147890849262, 
        0.08869640204235606, 
        0.09401857180866335
      ], 
      "nominal": [
        0.09927690072800033, 
        1.001197183286422, 
        1.457103820721386, 
        2.099250137398485, 
        0.09750954966875724, 
        0.8130766760223196, 
        1.3138158804213163, 
        1.511699186739861
      ], 
      "up": [
        0.024500922072510388, 
        0.07723341977373575, 
        0.09406905627862173, 
        0.11239901320032171, 
        0.02477813238324357, 
        0.06961147890849262, 
        0.08869640204235606, 
        0.09401857180866335
      ], 
      "bins": [
        [
          8.5, 
          9.5
        ], 
        [
          9.5, 
          10.5
        ], 
        [
          10.5, 
          11.5
        ], 
        [
          11.5, 
          12.5
        ], 
        [
          12.5, 
          13.5
        ], 
        [
          13.5, 
          14.5
        ], 
        [
          14.5, 
          15.5
        ], 
        [
          15.5, 
          16.5
        ]
      ]
    }, 
    "HNL-tau-m30-Vsq5.0em04-displaced": {
      "down": [
        0.17669057497213167, 
        0.5344507290979563, 
        0.5418432532683035, 
        0.0, 
        0.12122526219220017, 
        0.7199477673235806, 
        0.23558002021855112, 
        0.0
      ], 
      "nominal": [
        1.3929099972331696, 
        6.10110551851496, 
        5.615542679342308, 
        0.0, 
        0.5776822363398362, 
        4.208200518842433, 
        2.0777244999256963, 
        0.0
      ], 
      "up": [
        0.17669057497213167, 
        0.5344507290979563, 
        0.5418432532683035, 
        0.0, 
        0.12122526219220017, 
        0.7199477673235806, 
        0.23558002021855112, 
        0.0
      ], 
      "bins": [
        [
          8.5, 
          9.5
        ], 
        [
          9.5, 
          10.5
        ], 
        [
          10.5, 
          11.5
        ], 
        [
          11.5, 
          12.5
        ], 
        [
          12.5, 
          13.5
        ], 
        [
          13.5, 
          14.5
        ], 
        [
          14.5, 
          15.5
        ], 
        [
          15.5, 
          16.5
        ]
      ]
    }, 
    "HNL-e-m20-Vsq2.5em05-displaced": {
      "down": [
        0.0, 
        0.0, 
        0.0, 
        0.0, 
        0.0, 
        0.0, 
        0.0, 
        0.0
      ], 
      "nominal": [
        0.0, 
        0.0, 
        0.0, 
        0.0, 
        0.0, 
        0.0, 
        0.0, 
        0.0
      ], 
      "up": [
        0.0, 
        0.0, 
        0.0, 
        0.0, 
        0.0, 
        0.0, 
        0.0, 
        0.0
      ], 
      "bins": [
        [
          8.5, 
          9.5
        ], 
        [
          9.5, 
          10.5
        ], 
        [
          10.5, 
          11.5
        ], 
        [
          11.5, 
          12.5
        ], 
        [
          12.5, 
          13.5
        ], 
        [
          13.5, 
          14.5
        ], 
        [
          14.5, 
          15.5
        ], 
        [
          15.5, 
          16.5
        ]
      ]
    }, 
    "HNL-tau-m50-Vsq7.0em04-prompt": {
      "down": [
        0.02412795982330501, 
        0.060117583045468576, 
        0.08021758990848929, 
        0.10048170871357531, 
        0.01776228141112604, 
        0.049332520843212845, 
        0.05783443292787338, 
        0.06333402165937571
      ], 
      "nominal": [
        0.22738503154323553, 
        1.414828600758483, 
        2.4585933165326423, 
        3.7833471359735995, 
        0.12285602308475063, 
        0.9352774570434121, 
        1.3077625846635783, 
        1.5420787557050062
      ], 
      "up": [
        0.02412795982330501, 
        0.060117583045468576, 
        0.08021758990848929, 
        0.10048170871357531, 
        0.01776228141112604, 
        0.049332520843212845, 
        0.05783443292787338, 
        0.06333402165937571
      ], 
      "bins": [
        [
          8.5, 
          9.5
        ], 
        [
          9.5, 
          10.5
        ], 
        [
          10.5, 
          11.5
        ], 
        [
          11.5, 
          12.5
        ], 
        [
          12.5, 
          13.5
        ], 
        [
          13.5, 
          14.5
        ], 
        [
          14.5, 
          15.5
        ], 
        [
          15.5, 
          16.5
        ]
      ]
    }, 
    "HNL-e-m17.5-Vsq2.5em05-displaced": {
      "down": [
        0.0, 
        0.0, 
        0.0, 
        0.0, 
        0.0, 
        0.0, 
        0.0, 
        0.0
      ], 
      "nominal": [
        0.0, 
        0.0, 
        0.0, 
        0.0, 
        0.0, 
        0.0, 
        0.0, 
        0.0
      ], 
      "up": [
        0.0, 
        0.0, 
        0.0, 
        0.0, 
        0.0, 
        0.0, 
        0.0, 
        0.0
      ], 
      "bins": [
        [
          8.5, 
          9.5
        ], 
        [
          9.5, 
          10.5
        ], 
        [
          10.5, 
          11.5
        ], 
        [
          11.5, 
          12.5
        ], 
        [
          12.5, 
          13.5
        ], 
        [
          13.5, 
          14.5
        ], 
        [
          14.5, 
          15.5
        ], 
        [
          15.5, 
          16.5
        ]
      ]
    }, 
    "HNL-e-m15-Vsq2.5em05-displaced": {
      "down": [
        0.0, 
        0.0, 
        0.0, 
        0.0, 
        0.0, 
        0.0, 
        0.0, 
        0.0
      ], 
      "nominal": [
        0.0, 
        0.0, 
        0.0, 
        0.0, 
        0.0, 
        0.0, 
        0.0, 
        0.0
      ], 
      "up": [
        0.0, 
        0.0, 
        0.0, 
        0.0, 
        0.0, 
        0.0, 
        0.0, 
        0.0
      ], 
      "bins": [
        [
          8.5, 
          9.5
        ], 
        [
          9.5, 
          10.5
        ], 
        [
          10.5, 
          11.5
        ], 
        [
          11.5, 
          12.5
        ], 
        [
          12.5, 
          13.5
        ], 
        [
          13.5, 
          14.5
        ], 
        [
          14.5, 
          15.5
        ], 
        [
          15.5, 
          16.5
        ]
      ]
    }, 
    "HNL-e-m10-Vsq2.5em05-displaced": {
      "down": [
        0.0, 
        0.0, 
        0.0, 
        0.0, 
        0.0, 
        0.0, 
        0.0, 
        0.0
      ], 
      "nominal": [
        0.0, 
        0.0, 
        0.0, 
        0.0, 
        0.0, 
        0.0, 
        0.0, 
        0.0
      ], 
      "up": [
        0.0, 
        0.0, 
        0.0, 
        0.0, 
        0.0, 
        0.0, 
        0.0, 
        0.0
      ], 
      "bins": [
        [
          8.5, 
          9.5
        ], 
        [
          9.5, 
          10.5
        ], 
        [
          10.5, 
          11.5
        ], 
        [
          11.5, 
          12.5
        ], 
        [
          12.5, 
          13.5
        ], 
        [
          13.5, 
          14.5
        ], 
        [
          14.5, 
          15.5
        ], 
        [
          15.5, 
          16.5
        ]
      ]
    }, 
    "HNL-e-m60-Vsq2.0em05-prompt": {
      "down": [
        0.0004958142526447773, 
        0.0, 
        0.0008025619201362133, 
        0.0004759165924042464, 
        0.0, 
        0.0, 
        0.0004826303105801344, 
        0.0017936091870069506
      ], 
      "nominal": [
        0.0004958142526447773, 
        0.0, 
        0.0008025619201362133, 
        0.0004759165924042464, 
        0.0, 
        0.0, 
        0.0004826303105801344, 
        0.0017936091870069506
      ], 
      "up": [
        0.0004958142526447773, 
        0.0, 
        0.0008025619201362133, 
        0.0004759165924042464, 
        0.0, 
        0.0, 
        0.0004826303105801344, 
        0.0017936091870069506
      ], 
      "bins": [
        [
          8.5, 
          9.5
        ], 
        [
          9.5, 
          10.5
        ], 
        [
          10.5, 
          11.5
        ], 
        [
          11.5, 
          12.5
        ], 
        [
          12.5, 
          13.5
        ], 
        [
          13.5, 
          14.5
        ], 
        [
          14.5, 
          15.5
        ], 
        [
          15.5, 
          16.5
        ]
      ]
    }, 
    "HNL-tau-m40-Vsq6.0em04-prompt": {
      "down": [
        0.07012566554393278, 
        0.15973168001673152, 
        0.21904165299571132, 
        0.1690980071411707, 
        0.04912768227082934, 
        0.12378661443078166, 
        0.13883171098646593, 
        0.09596016164180612
      ], 
      "nominal": [
        0.5909929017070681, 
        3.0616278886736836, 
        5.650162967198412, 
        3.3120736872951966, 
        0.29690738665522076, 
        1.810679422749672, 
        2.2510260532144457, 
        1.136566067871172
      ], 
      "up": [
        0.07012566554393278, 
        0.15973168001673152, 
        0.21904165299571132, 
        0.1690980071411707, 
        0.04912768227082934, 
        0.12378661443078166, 
        0.13883171098646593, 
        0.09596016164180612
      ], 
      "bins": [
        [
          8.5, 
          9.5
        ], 
        [
          9.5, 
          10.5
        ], 
        [
          10.5, 
          11.5
        ], 
        [
          11.5, 
          12.5
        ], 
        [
          12.5, 
          13.5
        ], 
        [
          13.5, 
          14.5
        ], 
        [
          14.5, 
          15.5
        ], 
        [
          15.5, 
          16.5
        ]
      ]
    }, 
    "HNL-mu-m17.5-Vsq2.5em05-displaced": {
      "down": [
        0.0, 
        0.0, 
        0.0, 
        0.00013752087512124551, 
        0.0, 
        0.0, 
        0.0017163864602682852, 
        0.0
      ], 
      "nominal": [
        0.0, 
        0.0, 
        0.0, 
        0.00013752087512124551, 
        0.0, 
        0.0, 
        0.0017357765354663178, 
        0.0
      ], 
      "up": [
        0.0, 
        0.0, 
        0.0, 
        0.00013752087512124551, 
        0.0, 
        0.0, 
        0.0017163864602682852, 
        0.0
      ], 
      "bins": [
        [
          8.5, 
          9.5
        ], 
        [
          9.5, 
          10.5
        ], 
        [
          10.5, 
          11.5
        ], 
        [
          11.5, 
          12.5
        ], 
        [
          12.5, 
          13.5
        ], 
        [
          13.5, 
          14.5
        ], 
        [
          14.5, 
          15.5
        ], 
        [
          15.5, 
          16.5
        ]
      ]
    }, 
    "HNL-mu-m75-Vsq1.0em04-prompt": {
      "down": [
        0.0004068262060172856, 
        0.0004060223162778751, 
        0.0007992212216456874, 
        0.0007095627694987344, 
        0.0, 
        0.0011793680761571369, 
        0.0010060095980837032, 
        0.0009538202189906535
      ], 
      "nominal": [
        0.0004068262060172856, 
        0.0005340961215551943, 
        0.0017467620345996693, 
        0.0014144156448310241, 
        0.0, 
        0.0024219241458922625, 
        0.002181105788622517, 
        0.0023799850459909067
      ], 
      "up": [
        0.0004068262060172856, 
        0.0004060223162778751, 
        0.0007992212216456874, 
        0.0007095627694987344, 
        0.0, 
        0.0011793680761571369, 
        0.0010060095980837032, 
        0.0009538202189906535
      ], 
      "bins": [
        [
          8.5, 
          9.5
        ], 
        [
          9.5, 
          10.5
        ], 
        [
          10.5, 
          11.5
        ], 
        [
          11.5, 
          12.5
        ], 
        [
          12.5, 
          13.5
        ], 
        [
          13.5, 
          14.5
        ], 
        [
          14.5, 
          15.5
        ], 
        [
          15.5, 
          16.5
        ]
      ]
    }, 
    "HNL-e-m30-Vsq2.5em06-displaced": {
      "down": [
        0.0, 
        0.0, 
        0.001451446011902795, 
        0.0, 
        0.0, 
        0.0, 
        0.0007645565811891521, 
        0.0
      ], 
      "nominal": [
        0.0, 
        0.0, 
        0.0016353992026969595, 
        0.0, 
        0.0, 
        0.0, 
        0.0007645565811891521, 
        0.0
      ], 
      "up": [
        0.0, 
        0.0, 
        0.001451446011902795, 
        0.0, 
        0.0, 
        0.0, 
        0.0007645565811891521, 
        0.0
      ], 
      "bins": [
        [
          8.5, 
          9.5
        ], 
        [
          9.5, 
          10.5
        ], 
        [
          10.5, 
          11.5
        ], 
        [
          11.5, 
          12.5
        ], 
        [
          12.5, 
          13.5
        ], 
        [
          13.5, 
          14.5
        ], 
        [
          14.5, 
          15.5
        ], 
        [
          15.5, 
          16.5
        ]
      ]
    }, 
    "HNL-mu-m40-Vsq2.0em06-prompt": {
      "down": [
        0.0, 
        0.00042959523824212515, 
        0.0004042105726177526, 
        0.001006809103504341, 
        0.0, 
        0.000447974324788987, 
        0.00031326883618417833, 
        0.00021797874617091338
      ], 
      "nominal": [
        0.0, 
        0.0008529066620394589, 
        0.0007019278081133962, 
        0.003526481391163543, 
        0.0, 
        0.0009375987853854895, 
        0.00042574821040034297, 
        0.0003774323221296072
      ], 
      "up": [
        0.0, 
        0.00042959523824212515, 
        0.0004042105726177526, 
        0.001006809103504341, 
        0.0, 
        0.000447974324788987, 
        0.00031326883618417833, 
        0.00021797874617091338
      ], 
      "bins": [
        [
          8.5, 
          9.5
        ], 
        [
          9.5, 
          10.5
        ], 
        [
          10.5, 
          11.5
        ], 
        [
          11.5, 
          12.5
        ], 
        [
          12.5, 
          13.5
        ], 
        [
          13.5, 
          14.5
        ], 
        [
          14.5, 
          15.5
        ], 
        [
          15.5, 
          16.5
        ]
      ]
    }, 
    "HNL-mu-m30-Vsq2.5em05-displaced": {
      "down": [
        0.0, 
        4.9959884186332395e-06, 
        0.00013731083248462868, 
        0.12324424553714988, 
        0.0, 
        0.0, 
        0.0, 
        0.0
      ], 
      "nominal": [
        0.0, 
        4.9959884186332395e-06, 
        0.00013731083248468706, 
        0.12365269990484701, 
        0.0, 
        0.0, 
        0.0, 
        0.0
      ], 
      "up": [
        0.0, 
        4.9959884186332395e-06, 
        0.00013731083248462868, 
        0.12324424553714988, 
        0.0, 
        0.0, 
        0.0, 
        0.0
      ], 
      "bins": [
        [
          8.5, 
          9.5
        ], 
        [
          9.5, 
          10.5
        ], 
        [
          10.5, 
          11.5
        ], 
        [
          11.5, 
          12.5
        ], 
        [
          12.5, 
          13.5
        ], 
        [
          13.5, 
          14.5
        ], 
        [
          14.5, 
          15.5
        ], 
        [
          15.5, 
          16.5
        ]
      ]
    }, 
    "HNL-e-m50-Vsq1.0em05-prompt": {
      "down": [
        0.0, 
        0.0, 
        0.0, 
        0.0, 
        0.0, 
        0.0, 
        0.0, 
        0.0003918960224837065
      ], 
      "nominal": [
        0.0, 
        0.0, 
        0.0, 
        0.0, 
        0.0, 
        0.0, 
        0.0, 
        0.0003918960224837065
      ], 
      "up": [
        0.0, 
        0.0, 
        0.0, 
        0.0, 
        0.0, 
        0.0, 
        0.0, 
        0.0003918960224837065
      ], 
      "bins": [
        [
          8.5, 
          9.5
        ], 
        [
          9.5, 
          10.5
        ], 
        [
          10.5, 
          11.5
        ], 
        [
          11.5, 
          12.5
        ], 
        [
          12.5, 
          13.5
        ], 
        [
          13.5, 
          14.5
        ], 
        [
          14.5, 
          15.5
        ], 
        [
          15.5, 
          16.5
        ]
      ]
    }, 
    "HNL-tau-m75-Vsq3.0em02-prompt": {
      "down": [
        0.055794678401502276, 
        0.15406334785200135, 
        0.19859049731896652, 
        0.26325345274405876, 
        0.05877096183668148, 
        0.1911947067136936, 
        0.2135082329943533, 
        0.23012103860684435
      ], 
      "nominal": [
        0.17279919193242677, 
        1.253596140531954, 
        2.104102127304941, 
        3.6072769993552356, 
        0.19448072907835012, 
        1.9066110840867623, 
        2.3262785265160346, 
        2.69491767121508
      ], 
      "up": [
        0.055794678401502276, 
        0.15406334785200135, 
        0.19859049731896652, 
        0.26325345274405876, 
        0.05877096183668148, 
        0.1911947067136936, 
        0.2135082329943533, 
        0.23012103860684435
      ], 
      "bins": [
        [
          8.5, 
          9.5
        ], 
        [
          9.5, 
          10.5
        ], 
        [
          10.5, 
          11.5
        ], 
        [
          11.5, 
          12.5
        ], 
        [
          12.5, 
          13.5
        ], 
        [
          13.5, 
          14.5
        ], 
        [
          14.5, 
          15.5
        ], 
        [
          15.5, 
          16.5
        ]
      ]
    }, 
    "HNL-mu-m12.5-Vsq2.5em05-displaced": {
      "down": [
        0.010931795782002677, 
        0.01045360000322994, 
        0.0, 
        0.003594510595543022, 
        0.037997022499784774, 
        0.0021833807651929324, 
        0.0, 
        0.0072919303559468495
      ], 
      "nominal": [
        0.010931795782002677, 
        0.013954258875555365, 
        0.0, 
        0.003594510595543022, 
        0.037997022499784774, 
        0.0021833807651929324, 
        0.0, 
        0.0072919303559468495
      ], 
      "up": [
        0.010931795782002677, 
        0.01045360000322994, 
        0.0, 
        0.003594510595543022, 
        0.037997022499784774, 
        0.0021833807651929324, 
        0.0, 
        0.0072919303559468495
      ], 
      "bins": [
        [
          8.5, 
          9.5
        ], 
        [
          9.5, 
          10.5
        ], 
        [
          10.5, 
          11.5
        ], 
        [
          11.5, 
          12.5
        ], 
        [
          12.5, 
          13.5
        ], 
        [
          13.5, 
          14.5
        ], 
        [
          14.5, 
          15.5
        ], 
        [
          15.5, 
          16.5
        ]
      ]
    }, 
    "HNL-e-m75-Vsq5.0em04-prompt": {
      "down": [
        0.0, 
        0.0, 
        0.0010973682947224006, 
        0.002679250120728562, 
        0.0, 
        0.0, 
        0.0, 
        0.002138019366073283
      ], 
      "nominal": [
        0.0, 
        0.0, 
        0.0010973682947224006, 
        0.003492611213005148, 
        0.0, 
        0.0, 
        0.0, 
        0.002799849971779622
      ], 
      "up": [
        0.0, 
        0.0, 
        0.0010973682947224006, 
        0.002679250120728562, 
        0.0, 
        0.0, 
        0.0, 
        0.002138019366073283
      ], 
      "bins": [
        [
          8.5, 
          9.5
        ], 
        [
          9.5, 
          10.5
        ], 
        [
          10.5, 
          11.5
        ], 
        [
          11.5, 
          12.5
        ], 
        [
          12.5, 
          13.5
        ], 
        [
          13.5, 
          14.5
        ], 
        [
          14.5, 
          15.5
        ], 
        [
          15.5, 
          16.5
        ]
      ]
    }, 
    "HNL-mu-m15-Vsq2.5em05-displaced": {
      "down": [
        0.0, 
        0.0, 
        0.0, 
        1.288179437063111e-05, 
        0.0, 
        0.006438232119202372, 
        0.0, 
        2.635096855707698e-05
      ], 
      "nominal": [
        0.0, 
        0.0, 
        0.0, 
        1.288179437063111e-05, 
        0.0, 
        0.006438232119202372, 
        0.0, 
        2.635096855707698e-05
      ], 
      "up": [
        0.0, 
        0.0, 
        0.0, 
        1.288179437063111e-05, 
        0.0, 
        0.006438232119202372, 
        0.0, 
        2.635096855707698e-05
      ], 
      "bins": [
        [
          8.5, 
          9.5
        ], 
        [
          9.5, 
          10.5
        ], 
        [
          10.5, 
          11.5
        ], 
        [
          11.5, 
          12.5
        ], 
        [
          12.5, 
          13.5
        ], 
        [
          13.5, 
          14.5
        ], 
        [
          14.5, 
          15.5
        ], 
        [
          15.5, 
          16.5
        ]
      ]
    }, 
    "HNL-tau-m15-Vsq5.0em04-displaced": {
      "down": [
        0.45683601439499305, 
        0.3890393592931868, 
        0.0, 
        0.0, 
        0.33500415579215664, 
        0.29759985047748155, 
        0.0, 
        0.018785237984887015
      ], 
      "nominal": [
        5.354479446996755, 
        4.936796614221238, 
        0.0, 
        0.0, 
        3.81095504895408, 
        3.184676089292967, 
        0.0, 
        0.018785237984887015
      ], 
      "up": [
        0.45683601439499305, 
        0.3890393592931868, 
        0.0, 
        0.0, 
        0.33500415579215664, 
        0.29759985047748155, 
        0.0, 
        0.018785237984887015
      ], 
      "bins": [
        [
          8.5, 
          9.5
        ], 
        [
          9.5, 
          10.5
        ], 
        [
          10.5, 
          11.5
        ], 
        [
          11.5, 
          12.5
        ], 
        [
          12.5, 
          13.5
        ], 
        [
          13.5, 
          14.5
        ], 
        [
          14.5, 
          15.5
        ], 
        [
          15.5, 
          16.5
        ]
      ]
    }, 
    "HNL-e-m25-Vsq2.5em05-displaced": {
      "down": [
        0.0, 
        0.0, 
        0.0, 
        0.0, 
        0.0, 
        0.0, 
        0.0, 
        0.0
      ], 
      "nominal": [
        0.0, 
        0.0, 
        0.0, 
        0.0, 
        0.0, 
        0.0, 
        0.0, 
        0.0
      ], 
      "up": [
        0.0, 
        0.0, 
        0.0, 
        0.0, 
        0.0, 
        0.0, 
        0.0, 
        0.0
      ], 
      "bins": [
        [
          8.5, 
          9.5
        ], 
        [
          9.5, 
          10.5
        ], 
        [
          10.5, 
          11.5
        ], 
        [
          11.5, 
          12.5
        ], 
        [
          12.5, 
          13.5
        ], 
        [
          13.5, 
          14.5
        ], 
        [
          14.5, 
          15.5
        ], 
        [
          15.5, 
          16.5
        ]
      ]
    }, 
    "HNL-tau-m17.5-Vsq5.0em04-displaced": {
      "down": [
        3.1212086288981893, 
        0.4855428106764964, 
        0.0, 
        0.0, 
        0.32848697350718126, 
        0.7806914122108048, 
        0.0, 
        0.0
      ], 
      "nominal": [
        7.2249969387362, 
        6.385028144035735, 
        0.0, 
        0.0, 
        2.808254793300848, 
        5.123332294164695, 
        0.0, 
        0.0
      ], 
      "up": [
        3.1212086288981893, 
        0.4855428106764964, 
        0.0, 
        0.0, 
        0.32848697350718126, 
        0.7806914122108048, 
        0.0, 
        0.0
      ], 
      "bins": [
        [
          8.5, 
          9.5
        ], 
        [
          9.5, 
          10.5
        ], 
        [
          10.5, 
          11.5
        ], 
        [
          11.5, 
          12.5
        ], 
        [
          12.5, 
          13.5
        ], 
        [
          13.5, 
          14.5
        ], 
        [
          14.5, 
          15.5
        ], 
        [
          15.5, 
          16.5
        ]
      ]
    }, 
    "HNL-mu-m50-Vsq3.0em06-prompt": {
      "down": [
        0.0, 
        0.00043426534183505037, 
        0.0007277843050479229, 
        0.0008316494590550269, 
        0.0, 
        0.00040659179913459767, 
        0.00037461579842389245, 
        0.0007032244578246479
      ], 
      "nominal": [
        0.0, 
        0.0007818542327731847, 
        0.002192120865220204, 
        0.0024042537761852145, 
        0.0, 
        0.0005663462681695819, 
        0.0006784982560202479, 
        0.0021270256885327398
      ], 
      "up": [
        0.0, 
        0.00043426534183505037, 
        0.0007277843050479229, 
        0.0008316494590550269, 
        0.0, 
        0.00040659179913459767, 
        0.00037461579842389245, 
        0.0007032244578246479
      ], 
      "bins": [
        [
          8.5, 
          9.5
        ], 
        [
          9.5, 
          10.5
        ], 
        [
          10.5, 
          11.5
        ], 
        [
          11.5, 
          12.5
        ], 
        [
          12.5, 
          13.5
        ], 
        [
          13.5, 
          14.5
        ], 
        [
          14.5, 
          15.5
        ], 
        [
          15.5, 
          16.5
        ]
      ]
    }, 
    "HNL-mu-m25-Vsq2.5em05-displaced": {
      "down": [
        0.0, 
        0.021296258261281592, 
        0.0, 
        0.016431931381837492, 
        0.0, 
        0.069241045414863, 
        0.0007821595999506694, 
        0.056043352240932286
      ], 
      "nominal": [
        0.0, 
        0.024141045190000297, 
        0.0, 
        0.016431931381837492, 
        0.0, 
        0.07026726603078251, 
        0.0007821599959649973, 
        0.05605424426397345
      ], 
      "up": [
        0.0, 
        0.021296258261281592, 
        0.0, 
        0.016431931381837492, 
        0.0, 
        0.069241045414863, 
        0.0007821595999506694, 
        0.056043352240932286
      ], 
      "bins": [
        [
          8.5, 
          9.5
        ], 
        [
          9.5, 
          10.5
        ], 
        [
          10.5, 
          11.5
        ], 
        [
          11.5, 
          12.5
        ], 
        [
          12.5, 
          13.5
        ], 
        [
          13.5, 
          14.5
        ], 
        [
          14.5, 
          15.5
        ], 
        [
          15.5, 
          16.5
        ]
      ]
    }
  }, 
  "bkgr": {
    "Total Background": {
      "down": [
        17.81610448470736, 
        21.699274940376082, 
        13.989702443850733, 
        12.438466011106382, 
        14.055792894583861, 
        18.010602681567466, 
        10.88890300938377, 
        9.673425727651493
      ], 
      "nominal": [
        1197.736572265625, 
        1454.89453125, 
        817.2051391601562, 
        669.0184326171875, 
        889.9179077148438, 
        1108.033447265625, 
        580.302978515625, 
        479.0424499511719
      ], 
      "up": [
        17.81610448470736, 
        21.699274940376082, 
        13.989702443850733, 
        12.438466011106382, 
        14.055792894583861, 
        18.010602681567466, 
        10.88890300938377, 
        9.673425727651493
      ], 
      "bins": [
        [
          8.5, 
          9.5
        ], 
        [
          9.5, 
          10.5
        ], 
        [
          10.5, 
          11.5
        ], 
        [
          11.5, 
          12.5
        ], 
        [
          12.5, 
          13.5
        ], 
        [
          13.5, 
          14.5
        ], 
        [
          14.5, 
          15.5
        ], 
        [
          15.5, 
          16.5
        ]
      ]
    }
  }
}